ColumnFile/__init__.py
ColumnFile/columnfile.py
ColumnFile/LocalColumnFile/__init__.py
ColumnFile/LocalColumnFile/localcolumnfile.py
ColumnFile/LocalColumnFile/logger.py
ColumnFile/LocalColumnFile/CSVExternalAlgorithm/__init__.py
ColumnFile/LocalColumnFile/CSVExternalAlgorithm/csvexternalalgorithm.py
ColumnFile-0.0.5.dist-info/METADATA
ColumnFile-0.0.5.dist-info/RECORD
ColumnFile-0.0.5.dist-info/WHEEL
ColumnFile-0.0.5.dist-info/top_level.txt
