Metadata-Version: 2.1
Name: ColumnFile
Version: 0.0.5
Summary: Simple library to manage local file storage within an application based on the concept of local partition and sort keys
Home-page: https://github.com/hlefebvr/column-file
Author: Henri Lefebvre
Author-email: henri.pasdecalais@yahoo.com
License: UNKNOWN
Platform: UNKNOWN
Classifier: Programming Language :: Python :: 3
Classifier: License :: OSI Approved :: MIT License
Classifier: Operating System :: OS Independent
